CHANGES.txt
MANIFEST.in
README.txt
setup.cfg
setup.py
archetypes/__init__.py
archetypes.uploadreferencewidget.egg-info/PKG-INFO
archetypes.uploadreferencewidget.egg-info/SOURCES.txt
archetypes.uploadreferencewidget.egg-info/dependency_links.txt
archetypes.uploadreferencewidget.egg-info/namespace_packages.txt
archetypes.uploadreferencewidget.egg-info/not-zip-safe
archetypes.uploadreferencewidget.egg-info/requires.txt
archetypes.uploadreferencewidget.egg-info/top_level.txt
archetypes/uploadreferencewidget/__init__.py
archetypes/uploadreferencewidget/config.py
archetypes/uploadreferencewidget/configure.zcml
archetypes/uploadreferencewidget/demo.py
archetypes/uploadreferencewidget/patch.py
archetypes/uploadreferencewidget/widget.py
archetypes/uploadreferencewidget/locales/archetypes.uploadreferencewidget.pot
archetypes/uploadreferencewidget/locales/da/LC_MESSAGES/archetypes.uploadreferencewidget.po
archetypes/uploadreferencewidget/locales/fr/LC_MESSAGES/archetypes.uploadreferencewidget.po
archetypes/uploadreferencewidget/locales/nl/LC_MESSAGES/archetypes.uploadreferencewidget.po
archetypes/uploadreferencewidget/profiles/default/metadata.xml
archetypes/uploadreferencewidget/profiles/default/skins.xml
archetypes/uploadreferencewidget/profiles/demo/archetype_tool.xml
archetypes/uploadreferencewidget/profiles/demo/types.xml
archetypes/uploadreferencewidget/profiles/demo/types/UploadReferenceWidgetDemo.xml
archetypes/uploadreferencewidget/skins/uploadreferencewidget/uploadreference.js
archetypes/uploadreferencewidget/skins/uploadreferencewidget/uploadreference.js.metadata
archetypes/uploadreferencewidget/skins/uploadreferencewidget/uploadreference.pt
archetypes/uploadreferencewidget/tests/URWTestCase.py
archetypes/uploadreferencewidget/tests/__init__.py
archetypes/uploadreferencewidget/tests/enfold.gif
archetypes/uploadreferencewidget/tests/enfold.pdf
archetypes/uploadreferencewidget/tests/test_widget.py
archetypes/uploadreferencewidget/tests/utils.py
archetypes/uploadreferencewidget/tests/widget.txt
docs/HISTORY.txt
docs/LICENSE.txt
docs/TODO.txt