Metadata-Version: 1.0
Name: archetypes.uploadreferencewidget
Version: 0.2.1
Summary: A widget for Archetypes with support for both uploading and referencing content.
Home-page: http://svn.plone.org/svn/archetypes/MoreFieldsAndWidgets/archetypes.uploadreferencewidget
Author: Dorneles Tremea
Author-email: dorneles@tremea.com
License: LGPL
Keywords: Relation Widget
Platform: UNKNOWN
Classifier: Framework :: Plone
Classifier: Programming Language :: Python
Classifier: Topic :: Software Development :: Libraries :: Python Modules
